[
    {
        "size": {
            ".data-delta": 0,
            ".text-delta": 0,
            ".text": 30312,
            ".data": 473,
            ".bss": 6610,
            ".bss-delta": 0
        },
        "module": "../.."
    },
    {
        "size": {
            ".data-delta": 0,
            ".text-delta": 0,
            ".text": 2112,
            ".data": 0,
            ".bss": 600,
            ".bss-delta": 0
        },
        "module": "BUILD/K66F"
    },
    {
        "size": {
            ".data-delta": 0,
            ".text-delta": 0,
            ".text": 142,
            ".data": 11,
            ".bss": 33,
            ".bss-delta": 0
        },
        "module": "[fill]"
    },
    {
        "size": {
            ".data-delta": 0,
            ".text-delta": 0,
            ".text": 31934,
            ".data": 2472,
            ".bss": 89,
            ".bss-delta": 0
        },
        "module": "[lib]/c.a"
    },
    {
        "size": {
            ".data-delta": 0,
            ".text-delta": 0,
            ".text": 3336,
            ".data": 0,
            ".bss": 0,
            ".bss-delta": 0
        },
        "module": "[lib]/gcc.a"
    },
    {
        "size": {
            ".data-delta": 0,
            ".text-delta": 0,
            ".text": 180,
            ".data": 4,
            ".bss": 28,
            ".bss-delta": 0
        },
        "module": "[lib]/misc"
    },
    {
        "size": {
            ".data-delta": 0,
            ".text-delta": 0,
            ".text": 32,
            ".data": 0,
            ".bss": 0,
            ".bss-delta": 0
        },
        "module": "[lib]/nosys.a"
    },
    {
        "summary": {
            "static_ram_delta": 0,
            "total_flash_delta": 0,
            "total_flash": 71008,
            "static_ram": 10320
        }
    }
]
